[
  {
    "termDesc": "Spring 2022",
    "CRN": "6734",
    "courseNumber": "107",
    "sequenceNumber": "01",
    "subjectDescription": "KNES Kinesiology &amp; Health Sci",
    "scheduleTypeDescription": "Lecture/Standard",
    "courseTitle": "Lifetime Wellness",
    "creditHours": null,
    "maximumEnrollment": 25,
    "waitCapacity": 25,
    "creditHourHigh": null,
    "creditHourLow": 1,
    "faculty": [
      {
        "bannerId": "366123",
        "displayName": "Bedell, Jill",
        "emailAddress": "jill.bedell@biola.edu",
        "primaryIndicator": true
      }
    ],
    "location": {
      "startDate": "01/10/2022",
      "endDate": "05/07/2022",
      "beginTime": null,
      "endTime": null,
      "building": "NONE",
      "buildingDescription": "None",
      "creditHourSession": 1,
      "hoursWeek": 1,
      "room": "ONLINE",
      "days": [],
      "dayNames": []
    }
  },
  {
    "termDesc": "Spring 2022",
    "CRN": "6735",
    "courseNumber": "107",
    "sequenceNumber": "02",
    "subjectDescription": "KNES Kinesiology &amp; Health Sci",
    "scheduleTypeDescription": "Lecture/Standard",
    "courseTitle": "Lifetime Wellness",
    "creditHours": null,
    "maximumEnrollment": 25,
    "waitCapacity": 25,
    "creditHourHigh": null,
    "creditHourLow": 1,
    "faculty": [
      {
        "bannerId": "366123",
        "displayName": "Bedell, Jill",
        "emailAddress": "jill.bedell@biola.edu",
        "primaryIndicator": true
      }
    ],
    "location": {
      "startDate": "01/10/2022",
      "endDate": "05/07/2022",
      "beginTime": null,
      "endTime": null,
      "building": "NONE",
      "buildingDescription": "None",
      "creditHourSession": 1,
      "hoursWeek": 1,
      "room": "ONLINE",
      "days": [],
      "dayNames": []
    }
  },
  {
    "termDesc": "Spring 2022",
    "CRN": "6736",
    "courseNumber": "107",
    "sequenceNumber": "03",
    "subjectDescription": "KNES Kinesiology &amp; Health Sci",
    "scheduleTypeDescription": "Lecture/Standard",
    "courseTitle": "Lifetime Wellness",
    "creditHours": null,
    "maximumEnrollment": 25,
    "waitCapacity": 25,
    "creditHourHigh": null,
    "creditHourLow": 1,
    "faculty": [
      {
        "bannerId": "366123",
        "displayName": "Bedell, Jill",
        "emailAddress": "jill.bedell@biola.edu",
        "primaryIndicator": true
      }
    ],
    "location": {
      "startDate": "01/10/2022",
      "endDate": "05/07/2022",
      "beginTime": null,
      "endTime": null,
      "building": "NONE",
      "buildingDescription": "None",
      "creditHourSession": 1,
      "hoursWeek": 1,
      "room": "ONLINE",
      "days": [],
      "dayNames": []
    }
  },
  {
    "termDesc": "Spring 2022",
    "CRN": "6737",
    "courseNumber": "107",
    "sequenceNumber": "04",
    "subjectDescription": "KNES Kinesiology &amp; Health Sci",
    "scheduleTypeDescription": "Lecture/Standard",
    "courseTitle": "Lifetime Wellness",
    "creditHours": null,
    "maximumEnrollment": 25,
    "waitCapacity": 25,
    "creditHourHigh": null,
    "creditHourLow": 1,
    "faculty": [
      {
        "bannerId": "366124",
        "displayName": "Park, Ji-Yeun",
        "emailAddress": "ji.yeun.park@biola.edu",
        "primaryIndicator": true
      }
    ],
    "location": {
      "startDate": "01/10/2022",
      "endDate": "05/07/2022",
      "beginTime": null,
      "endTime": null,
      "building": "NONE",
      "buildingDescription": "None",
      "creditHourSession": 1,
      "hoursWeek": 1,
      "room": "ONLINE",
      "days": [],
      "dayNames": []
    }
  },
  {
    "termDesc": "Spring 2022",
    "CRN": "6738",
    "courseNumber": "107",
    "sequenceNumber": "05",
    "subjectDescription": "KNES Kinesiology &amp; Health Sci",
    "scheduleTypeDescription": "Lecture/Standard",
    "courseTitle": "Lifetime Wellness",
    "creditHours": null,
    "maximumEnrollment": 25,
    "waitCapacity": 25,
    "creditHourHigh": null,
    "creditHourLow": 1,
    "faculty": [
      {
        "bannerId": "366124",
        "displayName": "Park, Ji-Yeun",
        "emailAddress": "ji.yeun.park@biola.edu",
        "primaryIndicator": true
      }
    ],
    "location": {
      "startDate": "01/10/2022",
      "endDate": "05/07/2022",
      "beginTime": null,
      "endTime": null,
      "building": "NONE",
      "buildingDescription": "None",
      "creditHourSession": 1,
      "hoursWeek": 1,
      "room": "ONLINE",
      "days": [],
      "dayNames": []
    }
  },
  {
    "termDesc": "Spring 2022",
    "CRN": "6739",
    "courseNumber": "107",
    "sequenceNumber": "06",
    "subjectDescription": "KNES Kinesiology &amp; Health Sci",
    "scheduleTypeDescription": "Lecture/Standard",
    "courseTitle": "Lifetime Wellness",
    "creditHours": null,
    "maximumEnrollment": 25,
    "waitCapacity": 25,
    "creditHourHigh": null,
    "creditHourLow": 1,
    "faculty": [
      {
        "bannerId": "366124",
        "displayName": "Park, Ji-Yeun",
        "emailAddress": "ji.yeun.park@biola.edu",
        "primaryIndicator": true
      }
    ],
    "location": {
      "startDate": "01/10/2022",
      "endDate": "05/07/2022",
      "beginTime": null,
      "endTime": null,
      "building": "NONE",
      "buildingDescription": "None",
      "creditHourSession": 1,
      "hoursWeek": 3,
      "room": "ONLINE",
      "days": [],
      "dayNames": []
    }
  },
  {
    "termDesc": "Spring 2022",
    "CRN": "6740",
    "courseNumber": "107",
    "sequenceNumber": "07",
    "subjectDescription": "KNES Kinesiology &amp; Health Sci",
    "scheduleTypeDescription": "Lecture/Standard",
    "courseTitle": "Lifetime Wellness",
    "creditHours": null,
    "maximumEnrollment": 25,
    "waitCapacity": 25,
    "creditHourHigh": null,
    "creditHourLow": 1,
    "faculty": [
      {
        "bannerId": "366125",
        "displayName": "Miller, Kelsey",
        "emailAddress": "kelsey.l.miller@biola.edu",
        "primaryIndicator": true
      }
    ],
    "location": {
      "startDate": "01/10/2022",
      "endDate": "05/07/2022",
      "beginTime": null,
      "endTime": null,
      "building": "NONE",
      "buildingDescription": "None",
      "creditHourSession": 1,
      "hoursWeek": 1,
      "room": "ONLINE",
      "days": [],
      "dayNames": []
    }
  },
  {
    "termDesc": "Spring 2022",
    "CRN": "6741",
    "courseNumber": "107",
    "sequenceNumber": "08",
    "subjectDescription": "KNES Kinesiology &amp; Health Sci",
    "scheduleTypeDescription": "Lecture/Standard",
    "courseTitle": "Lifetime Wellness",
    "creditHours": null,
    "maximumEnrollment": 25,
    "waitCapacity": 25,
    "creditHourHigh": null,
    "creditHourLow": 1,
    "faculty": [
      {
        "bannerId": "366124",
        "displayName": "Park, Ji-Yeun",
        "emailAddress": "ji.yeun.park@biola.edu",
        "primaryIndicator": true
      }
    ],
    "location": {
      "startDate": "01/10/2022",
      "endDate": "05/07/2022",
      "beginTime": null,
      "endTime": null,
      "building": "NONE",
      "buildingDescription": "None",
      "creditHourSession": 1,
      "hoursWeek": 1,
      "room": "ONLINE",
      "days": [],
      "dayNames": []
    }
  },
  {
    "termDesc": "Spring 2022",
    "CRN": "6742",
    "courseNumber": "107",
    "sequenceNumber": "09",
    "subjectDescription": "KNES Kinesiology &amp; Health Sci",
    "scheduleTypeDescription": "Lecture/Standard",
    "courseTitle": "Lifetime Wellness",
    "creditHours": null,
    "maximumEnrollment": 25,
    "waitCapacity": 25,
    "creditHourHigh": null,
    "creditHourLow": 1,
    "faculty": [
      {
        "bannerId": "366125",
        "displayName": "Miller, Kelsey",
        "emailAddress": "kelsey.l.miller@biola.edu",
        "primaryIndicator": true
      }
    ],
    "location": {
      "startDate": "01/10/2022",
      "endDate": "05/07/2022",
      "beginTime": null,
      "endTime": null,
      "building": "NONE",
      "buildingDescription": "None",
      "creditHourSession": 1,
      "hoursWeek": 1,
      "room": "ONLINE",
      "days": [],
      "dayNames": []
    }
  },
  {
    "termDesc": "Spring 2022",
    "CRN": "6743",
    "courseNumber": "107",
    "sequenceNumber": "10",
    "subjectDescription": "KNES Kinesiology &amp; Health Sci",
    "scheduleTypeDescription": "Lecture/Standard",
    "courseTitle": "Lifetime Wellness",
    "creditHours": null,
    "maximumEnrollment": 25,
    "waitCapacity": 25,
    "creditHourHigh": null,
    "creditHourLow": 1,
    "faculty": [
      {
        "bannerId": "366125",
        "displayName": "Miller, Kelsey",
        "emailAddress": "kelsey.l.miller@biola.edu",
        "primaryIndicator": true
      }
    ],
    "location": {
      "startDate": "01/10/2022",
      "endDate": "05/07/2022",
      "beginTime": null,
      "endTime": null,
      "building": "NONE",
      "buildingDescription": "None",
      "creditHourSession": 1,
      "hoursWeek": 1,
      "room": "ONLINE",
      "days": [],
      "dayNames": []
    }
  },
  {
    "termDesc": "Spring 2022",
    "CRN": "6744",
    "courseNumber": "107",
    "sequenceNumber": "11",
    "subjectDescription": "KNES Kinesiology &amp; Health Sci",
    "scheduleTypeDescription": "Lecture/Standard",
    "courseTitle": "Lifetime Wellness",
    "creditHours": null,
    "maximumEnrollment": 25,
    "waitCapacity": 25,
    "creditHourHigh": null,
    "creditHourLow": 1,
    "faculty": [
      {
        "bannerId": "366126",
        "displayName": "Galbadage, Don Thushara",
        "emailAddress": "don.galbadage@biola.edu",
        "primaryIndicator": true
      }
    ],
    "location": {
      "startDate": "01/10/2022",
      "endDate": "05/07/2022",
      "beginTime": null,
      "endTime": null,
      "building": "NONE",
      "buildingDescription": "None",
      "creditHourSession": 1,
      "hoursWeek": 1,
      "room": "ONLINE",
      "days": [],
      "dayNames": []
    }
  },
  {
    "termDesc": "Spring 2022",
    "CRN": "6745",
    "courseNumber": "107",
    "sequenceNumber": "12",
    "subjectDescription": "KNES Kinesiology &amp; Health Sci",
    "scheduleTypeDescription": "Lecture/Standard",
    "courseTitle": "Lifetime Wellness",
    "creditHours": null,
    "maximumEnrollment": 25,
    "waitCapacity": 25,
    "creditHourHigh": null,
    "creditHourLow": 1,
    "faculty": [
      {
        "bannerId": "366126",
        "displayName": "Galbadage, Don Thushara",
        "emailAddress": "don.galbadage@biola.edu",
        "primaryIndicator": true
      }
    ],
    "location": {
      "startDate": "01/10/2022",
      "endDate": "05/07/2022",
      "beginTime": null,
      "endTime": null,
      "building": "NONE",
      "buildingDescription": "None",
      "creditHourSession": 1,
      "hoursWeek": 1,
      "room": "ONLINE",
      "days": [],
      "dayNames": []
    }
  },
  {
    "termDesc": "Spring 2022",
    "CRN": "6746",
    "courseNumber": "107",
    "sequenceNumber": "13",
    "subjectDescription": "KNES Kinesiology &amp; Health Sci",
    "scheduleTypeDescription": "Lecture/Standard",
    "courseTitle": "Lifetime Wellness",
    "creditHours": null,
    "maximumEnrollment": 25,
    "waitCapacity": 25,
    "creditHourHigh": null,
    "creditHourLow": 1,
    "faculty": [
      {
        "bannerId": "366126",
        "displayName": "Galbadage, Don Thushara",
        "emailAddress": "don.galbadage@biola.edu",
        "primaryIndicator": true
      }
    ],
    "location": {
      "startDate": "01/10/2022",
      "endDate": "05/07/2022",
      "beginTime": null,
      "endTime": null,
      "building": "NONE",
      "buildingDescription": "None",
      "creditHourSession": 1,
      "hoursWeek": 1,
      "room": "ONLINE",
      "days": [],
      "dayNames": []
    }
  },
  {
    "termDesc": "Spring 2022",
    "CRN": "6747",
    "courseNumber": "107",
    "sequenceNumber": "14",
    "subjectDescription": "KNES Kinesiology &amp; Health Sci",
    "scheduleTypeDescription": "Lecture/Standard",
    "courseTitle": "Lifetime Wellness",
    "creditHours": null,
    "maximumEnrollment": 25,
    "waitCapacity": 25,
    "creditHourHigh": null,
    "creditHourLow": 1,
    "faculty": [
      {
        "bannerId": "366127",
        "displayName": "Altamirano, Kristianna",
        "emailAddress": "kristianna.altamirano@biola.edu",
        "primaryIndicator": true
      }
    ],
    "location": {
      "startDate": "01/10/2022",
      "endDate": "05/07/2022",
      "beginTime": null,
      "endTime": null,
      "building": "NONE",
      "buildingDescription": "None",
      "creditHourSession": 1,
      "hoursWeek": 1,
      "room": "ONLINE",
      "days": [],
      "dayNames": []
    }
  },
  {
    "termDesc": "Spring 2022",
    "CRN": "6754",
    "courseNumber": "107",
    "sequenceNumber": "15",
    "subjectDescription": "KNES Kinesiology &amp; Health Sci",
    "scheduleTypeDescription": "Lecture/Standard",
    "courseTitle": "Lifetime Wellness",
    "creditHours": null,
    "maximumEnrollment": 25,
    "waitCapacity": 25,
    "creditHourHigh": null,
    "creditHourLow": 1,
    "faculty": [
      {
        "bannerId": "366127",
        "displayName": "Altamirano, Kristianna",
        "emailAddress": "kristianna.altamirano@biola.edu",
        "primaryIndicator": true
      }
    ],
    "location": {
      "startDate": "01/10/2022",
      "endDate": "05/07/2022",
      "beginTime": null,
      "endTime": null,
      "building": "NONE",
      "buildingDescription": "None",
      "creditHourSession": 1,
      "hoursWeek": 1,
      "room": "ONLINE",
      "days": [],
      "dayNames": []
    }
  },
  {
    "termDesc": "Spring 2022",
    "CRN": "6771",
    "courseNumber": "107",
    "sequenceNumber": "16",
    "subjectDescription": "KNES Kinesiology &amp; Health Sci",
    "scheduleTypeDescription": "Lecture/Standard",
    "courseTitle": "Lifetime Wellness",
    "creditHours": null,
    "maximumEnrollment": 25,
    "waitCapacity": 25,
    "creditHourHigh": null,
    "creditHourLow": 1,
    "faculty": [
      {
        "bannerId": "366125",
        "displayName": "Miller, Kelsey",
        "emailAddress": "kelsey.l.miller@biola.edu",
        "primaryIndicator": true
      }
    ],
    "location": {
      "startDate": "01/10/2022",
      "endDate": "05/07/2022",
      "beginTime": null,
      "endTime": null,
      "building": "NONE",
      "buildingDescription": "None",
      "creditHourSession": 1,
      "hoursWeek": 1,
      "room": "ONLINE",
      "days": [],
      "dayNames": []
    }
  },
  {
    "termDesc": "Spring 2022",
    "CRN": "6774",
    "courseNumber": "107",
    "sequenceNumber": "17",
    "subjectDescription": "KNES Kinesiology &amp; Health Sci",
    "scheduleTypeDescription": "Lecture/Standard",
    "courseTitle": "Lifetime Wellness",
    "creditHours": null,
    "maximumEnrollment": 25,
    "waitCapacity": 25,
    "creditHourHigh": null,
    "creditHourLow": 1,
    "faculty": [
      {
        "bannerId": "366124",
        "displayName": "Park, Ji-Yeun",
        "emailAddress": "ji.yeun.park@biola.edu",
        "primaryIndicator": true
      }
    ],
    "location": {
      "startDate": "01/10/2022",
      "endDate": "05/07/2022",
      "beginTime": null,
      "endTime": null,
      "building": "NONE",
      "buildingDescription": "None",
      "creditHourSession": 1,
      "hoursWeek": 1,
      "room": "ONLINE",
      "days": [],
      "dayNames": []
    }
  },
  {
    "termDesc": "Spring 2022",
    "CRN": "6775",
    "courseNumber": "107",
    "sequenceNumber": "18",
    "subjectDescription": "KNES Kinesiology &amp; Health Sci",
    "scheduleTypeDescription": "Lecture/Standard",
    "courseTitle": "Lifetime Wellness",
    "creditHours": null,
    "maximumEnrollment": 25,
    "waitCapacity": 25,
    "creditHourHigh": null,
    "creditHourLow": 1,
    "faculty": [
      {
        "bannerId": "366124",
        "displayName": "Park, Ji-Yeun",
        "emailAddress": "ji.yeun.park@biola.edu",
        "primaryIndicator": true
      }
    ],
    "location": {
      "startDate": "01/10/2022",
      "endDate": "05/07/2022",
      "beginTime": null,
      "endTime": null,
      "building": "NONE",
      "buildingDescription": "None",
      "creditHourSession": 1,
      "hoursWeek": 1,
      "room": "ONLINE",
      "days": [],
      "dayNames": []
    }
  },
  {
    "termDesc": "Spring 2022",
    "CRN": "6002",
    "courseNumber": "110",
    "sequenceNumber": "02",
    "subjectDescription": "KNES Kinesiology &amp; Health Sci",
    "scheduleTypeDescription": "Swimming",
    "courseTitle": "Beg Swimming",
    "creditHours": null,
    "maximumEnrollment": 20,
    "waitCapacity": 30,
    "creditHourHigh": null,
    "creditHourLow": 1,
    "faculty": [
      {
        "bannerId": "366104",
        "displayName": "Cook, Nathanael",
        "emailAddress": "nathanael.d.cook@biola.edu",
        "primaryIndicator": true
      }
    ],
    "location": {
      "startDate": "01/10/2022",
      "endDate": "04/30/2022",
      "beginTime": "1100",
      "endTime": "1150",
      "building": "LANSNG",
      "buildingDescription": "Lansing Aquatic Center",
      "creditHourSession": 1,
      "hoursWeek": 1.66,
      "room": "POOL",
      "days": [
        "M",
        "W"
      ],
      "dayNames": [
        "Monday",
        "Wednesday"
      ]
    }
  },
  {
    "termDesc": "Spring 2022",
    "CRN": "6006",
    "courseNumber": "110",
    "sequenceNumber": "04",
    "subjectDescription": "KNES Kinesiology &amp; Health Sci",
    "scheduleTypeDescription": "Aerobics",
    "courseTitle": "Aerobics",
    "creditHours": null,
    "maximumEnrollment": 24,
    "waitCapacity": 24,
    "creditHourHigh": null,
    "creditHourLow": 1,
    "faculty": [
      {
        "bannerId": "366105",
        "displayName": "Pettis, Renda",
        "emailAddress": "renda.pettis@biola.edu",
        "primaryIndicator": true
      }
    ],
    "location": {
      "startDate": "01/10/2022",
      "endDate": "04/29/2022",
      "beginTime": "0930",
      "endTime": "1020",
      "building": "SOUBRU",
      "buildingDescription": "Soubirou Hall",
      "creditHourSession": 1,
      "hoursWeek": 1.66,
      "room": "202",
      "days": [
        "T",
        "R"
      ],
      "dayNames": [
        "Tuesday",
        "Thursday"
      ]
    }
  },
  {
    "termDesc": "Spring 2022",
    "CRN": "6007",
    "courseNumber": "110",
    "sequenceNumber": "05",
    "subjectDescription": "KNES Kinesiology &amp; Health Sci",
    "scheduleTypeDescription": "Stretch and Strength",
    "courseTitle": "Stretch &amp; Strength",
    "creditHours": null,
    "maximumEnrollment": 23,
    "waitCapacity": 25,
    "creditHourHigh": null,
    "creditHourLow": 1,
    "faculty": [
      {
        "bannerId": "366105",
        "displayName": "Pettis, Renda",
        "emailAddress": "renda.pettis@biola.edu",
        "primaryIndicator": true
      }
    ],
    "location": {
      "startDate": "01/10/2022",
      "endDate": "04/30/2022",
      "beginTime": "0730",
      "endTime": "0820",
      "building": "SOUBRU",
      "buildingDescription": "Soubirou Hall",
      "creditHourSession": 1,
      "hoursWeek": 1.66,
      "room": "202",
      "days": [
        "T",
        "R"
      ],
      "dayNames": [
        "Tuesday",
        "Thursday"
      ]
    }
  },
  {
    "termDesc": "Spring 2022",
    "CRN": "6008",
    "courseNumber": "110",
    "sequenceNumber": "06",
    "subjectDescription": "KNES Kinesiology &amp; Health Sci",
    "scheduleTypeDescription": "Stretch and Strength",
    "courseTitle": "Stretch &amp; Strength",
    "creditHours": null,
    "maximumEnrollment": 20,
    "waitCapacity": 25,
    "creditHourHigh": null,
    "creditHourLow": 1,
    "faculty": [
      {
        "bannerId": "366105",
        "displayName": "Pettis, Renda",
        "emailAddress": "renda.pettis@biola.edu",
        "primaryIndicator": true
      }
    ],
    "location": {
      "startDate": "01/10/2022",
      "endDate": "04/30/2022",
      "beginTime": "0830",
      "endTime": "0920",
      "building": "SOUBRU",
      "buildingDescription": "Soubirou Hall",
      "creditHourSession": 1,
      "hoursWeek": 1.66,
      "room": "202",
      "days": [
        "T",
        "R"
      ],
      "dayNames": [
        "Tuesday",
        "Thursday"
      ]
    }
  },
  {
    "termDesc": "Spring 2022",
    "CRN": "6009",
    "courseNumber": "110",
    "sequenceNumber": "07",
    "subjectDescription": "KNES Kinesiology &amp; Health Sci",
    "scheduleTypeDescription": "Stretch and Strength",
    "courseTitle": "Stretch &amp; Strength",
    "creditHours": null,
    "maximumEnrollment": 20,
    "waitCapacity": 25,
    "creditHourHigh": null,
    "creditHourLow": 1,
    "faculty": [
      {
        "bannerId": "366105",
        "displayName": "Pettis, Renda",
        "emailAddress": "renda.pettis@biola.edu",
        "primaryIndicator": true
      }
    ],
    "location": {
      "startDate": "01/10/2022",
      "endDate": "04/30/2022",
      "beginTime": "1030",
      "endTime": "1120",
      "building": "SOUBRU",
      "buildingDescription": "Soubirou Hall",
      "creditHourSession": 1,
      "hoursWeek": 1.66,
      "room": "202",
      "days": [
        "T",
        "R"
      ],
      "dayNames": [
        "Tuesday",
        "Thursday"
      ]
    }
  },
  {
    "termDesc": "Spring 2022",
    "CRN": "6010",
    "courseNumber": "110",
    "sequenceNumber": "08",
    "subjectDescription": "KNES Kinesiology &amp; Health Sci",
    "scheduleTypeDescription": "Condition for Rhythmic Movemnt",
    "courseTitle": "Beg Condtng for Rhythmic Mvmt",
    "creditHours": null,
    "maximumEnrollment": 23,
    "waitCapacity": 25,
    "creditHourHigh": null,
    "creditHourLow": 1,
    "faculty": [
      {
        "bannerId": "366105",
        "displayName": "Pettis, Renda",
        "emailAddress": "renda.pettis@biola.edu",
        "primaryIndicator": true
      }
    ],
    "location": {
      "startDate": "01/10/2022",
      "endDate": "04/30/2022",
      "beginTime": "0800",
      "endTime": "0929",
      "building": "SOUBRU",
      "buildingDescription": "Soubirou Hall",
      "creditHourSession": 1,
      "hoursWeek": 1.48,
      "room": "202",
      "days": [
        "W"
      ],
      "dayNames": [
        "Wednesday"
      ]
    }
  },
  {
    "termDesc": "Spring 2022",
    "CRN": "6012",
    "courseNumber": "110",
    "sequenceNumber": "12",
    "subjectDescription": "KNES Kinesiology &amp; Health Sci",
    "scheduleTypeDescription": "Archery",
    "courseTitle": "Beg Archery",
    "creditHours": null,
    "maximumEnrollment": 20,
    "waitCapacity": 25,
    "creditHourHigh": null,
    "creditHourLow": 1,
    "faculty": [
      {
        "bannerId": "366106",
        "displayName": "Gardner, Jacob",
        "emailAddress": "jake.gardner@biola.edu",
        "primaryIndicator": true
      }
    ],
    "location": {
      "startDate": "01/21/2022",
      "endDate": "04/30/2022",
      "beginTime": "1030",
      "endTime": "1200",
      "building": "STHCMP",
      "buildingDescription": "South Campus",
      "creditHourSession": 1,
      "hoursWeek": 1.5,
      "room": "ARCHERY",
      "days": [
        "F"
      ],
      "dayNames": [
        "Friday"
      ]
    }
  },
  {
    "termDesc": "Spring 2022",
    "CRN": "6014",
    "courseNumber": "110",
    "sequenceNumber": "13",
    "subjectDescription": "KNES Kinesiology &amp; Health Sci",
    "scheduleTypeDescription": "Disc Golf",
    "courseTitle": "Disc Golf",
    "creditHours": null,
    "maximumEnrollment": 25,
    "waitCapacity": 25,
    "creditHourHigh": null,
    "creditHourLow": 1,
    "faculty": [
      {
        "bannerId": "366107",
        "displayName": "Wiese, John",
        "emailAddress": "john.wiese@biola.edu",
        "primaryIndicator": true
      }
    ],
    "location": {
      "startDate": "01/10/2022",
      "endDate": "01/17/2022",
      "beginTime": "0800",
      "endTime": "0929",
      "building": "MYERS",
      "buildingDescription": "Myers Hall",
      "creditHourSession": 1,
      "hoursWeek": 1.48,
      "room": "108",
      "days": [
        "M"
      ],
      "dayNames": [
        "Monday"
      ]
    }
  },
  {
    "termDesc": "Spring 2022",
    "CRN": "6017",
    "courseNumber": "110",
    "sequenceNumber": "15",
    "subjectDescription": "KNES Kinesiology &amp; Health Sci",
    "scheduleTypeDescription": "Volleyball",
    "courseTitle": "Beg Volleyball",
    "creditHours": null,
    "maximumEnrollment": 24,
    "waitCapacity": 26,
    "creditHourHigh": null,
    "creditHourLow": 1,
    "faculty": [
      {
        "bannerId": "366108",
        "displayName": "Teague, Grace",
        "emailAddress": "grace.l.gallarda@biola.edu",
        "primaryIndicator": true
      }
    ],
    "location": {
      "startDate": "01/10/2022",
      "endDate": "04/30/2022",
      "beginTime": "1030",
      "endTime": "1120",
      "building": "CHASE",
      "buildingDescription": "Chase Gymnasium",
      "creditHourSession": 1,
      "hoursWeek": 1.66,
      "room": "GYMNASIUM",
      "days": [
        "T",
        "R"
      ],
      "dayNames": [
        "Tuesday",
        "Thursday"
      ]
    }
  },
  {
    "termDesc": "Spring 2022",
    "CRN": "6019",
    "courseNumber": "110",
    "sequenceNumber": "16",
    "subjectDescription": "KNES Kinesiology &amp; Health Sci",
    "scheduleTypeDescription": "Soccer",
    "courseTitle": "Beg Soccer - Coed",
    "creditHours": null,
    "maximumEnrollment": 22,
    "waitCapacity": 25,
    "creditHourHigh": null,
    "creditHourLow": 1,
    "faculty": [
      {
        "bannerId": "366109",
        "displayName": "Gizzi, Paul",
        "emailAddress": "paul.gizzi@biola.edu",
        "primaryIndicator": true
      }
    ],
    "location": {
      "startDate": "01/10/2022",
      "endDate": "04/30/2022",
      "beginTime": "1030",
      "endTime": "1120",
      "building": "ATHLTC",
      "buildingDescription": "Athletics",
      "creditHourSession": 1,
      "hoursWeek": 1.66,
      "room": "SOCCER",
      "days": [
        "M",
        "W"
      ],
      "dayNames": [
        "Monday",
        "Wednesday"
      ]
    }
  },
  {
    "termDesc": "Spring 2022",
    "CRN": "6023",
    "courseNumber": "110",
    "sequenceNumber": "18",
    "subjectDescription": "KNES Kinesiology &amp; Health Sci",
    "scheduleTypeDescription": "Weight Training",
    "courseTitle": "Weights Training - Coed",
    "creditHours": null,
    "maximumEnrollment": 25,
    "waitCapacity": 25,
    "creditHourHigh": null,
    "creditHourLow": 1,
    "faculty": [
      {
        "bannerId": "366110",
        "displayName": "Apkarian, Marc",
        "emailAddress": "marc.apkarian@biola.edu",
        "primaryIndicator": true
      }
    ],
    "location": {
      "startDate": "02/08/2022",
      "endDate": "04/28/2022",
      "beginTime": "1330",
      "endTime": "1430",
      "building": "SOUBRU",
      "buildingDescription": "Soubirou Hall",
      "creditHourSession": 1,
      "hoursWeek": 2,
      "room": "103",
      "days": [
        "M",
        "W"
      ],
      "dayNames": [
        "Monday",
        "Wednesday"
      ]
    }
  },
  {
    "termDesc": "Spring 2022",
    "CRN": "6024",
    "courseNumber": "110",
    "sequenceNumber": "19",
    "subjectDescription": "KNES Kinesiology &amp; Health Sci",
    "scheduleTypeDescription": "Weaponless Self Defense",
    "courseTitle": "Weaponless Self Defense",
    "creditHours": null,
    "maximumEnrollment": 16,
    "waitCapacity": 16,
    "creditHourHigh": null,
    "creditHourLow": 1,
    "faculty": [
      {
        "bannerId": "366025",
        "displayName": "Muehlhoff, Timothy",
        "emailAddress": "tim.muehlhoff@biola.edu",
        "primaryIndicator": true
      }
    ],
    "location": {
      "startDate": "01/10/2022",
      "endDate": "04/30/2022",
      "beginTime": "0800",
      "endTime": "0929",
      "building": "SOUBRU",
      "buildingDescription": "Soubirou Hall",
      "creditHourSession": 1,
      "hoursWeek": 1.48,
      "room": "202",
      "days": [
        "M"
      ],
      "dayNames": [
        "Monday"
      ]
    }
  },
  {
    "termDesc": "Spring 2022",
    "CRN": "6025",
    "courseNumber": "110",
    "sequenceNumber": "20",
    "subjectDescription": "KNES Kinesiology &amp; Health Sci",
    "scheduleTypeDescription": "Weaponless Self Defense",
    "courseTitle": "Weaponless Self Defense",
    "creditHours": null,
    "maximumEnrollment": 16,
    "waitCapacity": 16,
    "creditHourHigh": null,
    "creditHourLow": 1,
    "faculty": [
      {
        "bannerId": "366111",
        "displayName": "Pack, Eddie",
        "emailAddress": "eddie.pack@biola.edu",
        "primaryIndicator": true
      }
    ],
    "location": {
      "startDate": "01/10/2022",
      "endDate": "04/30/2022",
      "beginTime": "1800",
      "endTime": "1930",
      "building": "SOUBRU",
      "buildingDescription": "Soubirou Hall",
      "creditHourSession": 1,
      "hoursWeek": 1.5,
      "room": "202",
      "days": [
        "W"
      ],
      "dayNames": [
        "Wednesday"
      ]
    }
  },
  {
    "termDesc": "Spring 2022",
    "CRN": "6026",
    "courseNumber": "110",
    "sequenceNumber": "21",
    "subjectDescription": "KNES Kinesiology &amp; Health Sci",
    "scheduleTypeDescription": "RADS - Rape Agress/Defense",
    "courseTitle": "RADS (Women&#39;s Self Defense)",
    "creditHours": null,
    "maximumEnrollment": 16,
    "waitCapacity": 16,
    "creditHourHigh": null,
    "creditHourLow": 1,
    "faculty": [
      {
        "bannerId": "366112",
        "displayName": "Ojeisekhoba Sr, John",
        "emailAddress": "john.ojeisekhoba@biola.edu",
        "primaryIndicator": true
      }
    ],
    "location": {
      "startDate": "01/14/2022",
      "endDate": "01/14/2022",
      "beginTime": "1030",
      "endTime": "1430",
      "building": "ROSE",
      "buildingDescription": "Rose Hall",
      "creditHourSession": 1,
      "hoursWeek": 4,
      "room": "003",
      "days": [
        "F"
      ],
      "dayNames": [
        "Friday"
      ]
    }
  },
  {
    "termDesc": "Spring 2022",
    "CRN": "6029",
    "courseNumber": "110",
    "sequenceNumber": "24",
    "subjectDescription": "KNES Kinesiology &amp; Health Sci",
    "scheduleTypeDescription": "Rock Climbing",
    "courseTitle": "Rock Climbing",
    "creditHours": null,
    "maximumEnrollment": 20,
    "waitCapacity": 20,
    "creditHourHigh": null,
    "creditHourLow": 1,
    "faculty": [
      {
        "bannerId": "366113",
        "displayName": "Bedell, David",
        "emailAddress": "david.bedell@biola.edu",
        "primaryIndicator": true
      }
    ],
    "location": {
      "startDate": "03/26/2022",
      "endDate": "03/26/2022",
      "beginTime": "0900",
      "endTime": "1500",
      "building": "OFFCMP",
      "buildingDescription": "Off Campus",
      "creditHourSession": 0,
      "hoursWeek": 6,
      "room": "LOCATION",
      "days": [
        "S"
      ],
      "dayNames": [
        "Saturday"
      ]
    }
  },
  {
    "termDesc": "Spring 2022",
    "CRN": "6030",
    "courseNumber": "110",
    "sequenceNumber": "25",
    "subjectDescription": "KNES Kinesiology &amp; Health Sci",
    "scheduleTypeDescription": "Backpacking",
    "courseTitle": "Backpacking",
    "creditHours": null,
    "maximumEnrollment": 16,
    "waitCapacity": 20,
    "creditHourHigh": null,
    "creditHourLow": 1,
    "faculty": [
      {
        "bannerId": "366113",
        "displayName": "Bedell, David",
        "emailAddress": "david.bedell@biola.edu",
        "primaryIndicator": true
      }
    ],
    "location": {
      "startDate": "02/05/2022",
      "endDate": "04/23/2022",
      "beginTime": "0900",
      "endTime": "1700",
      "building": "OFFCMP",
      "buildingDescription": "Off Campus",
      "creditHourSession": 0,
      "hoursWeek": 8,
      "room": "LOCATION",
      "days": [
        "S"
      ],
      "dayNames": [
        "Saturday"
      ]
    }
  },
  {
    "termDesc": "Spring 2022",
    "CRN": "6031",
    "courseNumber": "110",
    "sequenceNumber": "30",
    "subjectDescription": "KNES Kinesiology &amp; Health Sci",
    "scheduleTypeDescription": "Basketball",
    "courseTitle": "Beg Basketball",
    "creditHours": null,
    "maximumEnrollment": 24,
    "waitCapacity": 24,
    "creditHourHigh": null,
    "creditHourLow": 1,
    "faculty": [
      {
        "bannerId": "366114",
        "displayName": "Cone, David",
        "emailAddress": "david.e.cone@biola.edu",
        "primaryIndicator": true
      }
    ],
    "location": {
      "startDate": "01/10/2022",
      "endDate": "04/30/2022",
      "beginTime": "1030",
      "endTime": "1129",
      "building": "CHASE",
      "buildingDescription": "Chase Gymnasium",
      "creditHourSession": 1,
      "hoursWeek": 1.96,
      "room": "GYMNASIUM",
      "days": [
        "M",
        "W"
      ],
      "dayNames": [
        "Monday",
        "Wednesday"
      ]
    }
  },
  {
    "termDesc": "Spring 2022",
    "CRN": "6033",
    "courseNumber": "110",
    "sequenceNumber": "31",
    "subjectDescription": "KNES Kinesiology &amp; Health Sci",
    "scheduleTypeDescription": "Basketball",
    "courseTitle": "Beg Basketball",
    "creditHours": null,
    "maximumEnrollment": 24,
    "waitCapacity": 24,
    "creditHourHigh": null,
    "creditHourLow": 1,
    "faculty": [
      {
        "bannerId": "366115",
        "displayName": "Holmquist, David",
        "emailAddress": "dave.holmquist@biola.edu",
        "primaryIndicator": true
      }
    ],
    "location": {
      "startDate": "01/10/2022",
      "endDate": "04/30/2022",
      "beginTime": "1200",
      "endTime": "1250",
      "building": "CHASE",
      "buildingDescription": "Chase Gymnasium",
      "creditHourSession": 1,
      "hoursWeek": 1.66,
      "room": "GYMNASIUM",
      "days": [
        "M",
        "W"
      ],
      "dayNames": [
        "Monday",
        "Wednesday"
      ]
    }
  },
  {
    "termDesc": "Spring 2022",
    "CRN": "6038",
    "courseNumber": "110",
    "sequenceNumber": "33",
    "subjectDescription": "KNES Kinesiology &amp; Health Sci",
    "scheduleTypeDescription": "Tennis",
    "courseTitle": "Beg Tennis",
    "creditHours": null,
    "maximumEnrollment": 14,
    "waitCapacity": 14,
    "creditHourHigh": null,
    "creditHourLow": 1,
    "faculty": [
      {
        "bannerId": "366116",
        "displayName": "Goodman, David",
        "emailAddress": "david.t.goodman@biola.edu",
        "primaryIndicator": true
      }
    ],
    "location": {
      "startDate": "01/10/2022",
      "endDate": "04/30/2022",
      "beginTime": "1030",
      "endTime": "1120",
      "building": "TENNIS",
      "buildingDescription": "Tennis Center",
      "creditHourSession": 1,
      "hoursWeek": 1.66,
      "room": "COURTS",
      "days": [
        "T",
        "R"
      ],
      "dayNames": [
        "Tuesday",
        "Thursday"
      ]
    }
  },
  {
    "termDesc": "Spring 2022",
    "CRN": "6042",
    "courseNumber": "110",
    "sequenceNumber": "35",
    "subjectDescription": "KNES Kinesiology &amp; Health Sci",
    "scheduleTypeDescription": "Walking/Running",
    "courseTitle": "Walking/Running",
    "creditHours": null,
    "maximumEnrollment": 25,
    "waitCapacity": 25,
    "creditHourHigh": null,
    "creditHourLow": 1,
    "faculty": [
      {
        "bannerId": "366117",
        "displayName": "Henning, Sean",
        "emailAddress": "sean.henning@biola.edu",
        "primaryIndicator": true
      }
    ],
    "location": {
      "startDate": "01/10/2022",
      "endDate": "04/30/2022",
      "beginTime": "1030",
      "endTime": "1120",
      "building": "ATHLTC",
      "buildingDescription": "Athletics",
      "creditHourSession": 1,
      "hoursWeek": 1.66,
      "room": "TRACK",
      "days": [
        "M",
        "W"
      ],
      "dayNames": [
        "Monday",
        "Wednesday"
      ]
    }
  },
  {
    "termDesc": "Spring 2022",
    "CRN": "6043",
    "courseNumber": "118",
    "sequenceNumber": "01",
    "subjectDescription": "KNES Kinesiology &amp; Health Sci",
    "scheduleTypeDescription": "Baseball - Men",
    "courseTitle": "Varsity Baseball - Men",
    "creditHours": null,
    "maximumEnrollment": 50,
    "waitCapacity": 50,
    "creditHourHigh": null,
    "creditHourLow": 1,
    "faculty": [
      {
        "bannerId": "365896",
        "displayName": "Shepard, Edmond",
        "emailAddress": "edmond.e.shepard@biola.edu",
        "primaryIndicator": true
      }
    ],
    "location": {
      "startDate": "01/10/2022",
      "endDate": "05/07/2022",
      "beginTime": null,
      "endTime": null,
      "building": "NONE",
      "buildingDescription": "None",
      "creditHourSession": 1,
      "hoursWeek": 1,
      "room": "VARIED",
      "days": [],
      "dayNames": []
    }
  },
  {
    "termDesc": "Spring 2022",
    "CRN": "6044",
    "courseNumber": "118",
    "sequenceNumber": "02",
    "subjectDescription": "KNES Kinesiology &amp; Health Sci",
    "scheduleTypeDescription": "Basketball - Men",
    "courseTitle": "Varsity Basketball - Men",
    "creditHours": null,
    "maximumEnrollment": 50,
    "waitCapacity": 50,
    "creditHourHigh": null,
    "creditHourLow": 1,
    "faculty": [
      {
        "bannerId": "366115",
        "displayName": "Holmquist, David",
        "emailAddress": "dave.holmquist@biola.edu",
        "primaryIndicator": true
      }
    ],
    "location": {
      "startDate": "01/10/2022",
      "endDate": "05/07/2022",
      "beginTime": null,
      "endTime": null,
      "building": "NONE",
      "buildingDescription": "None",
      "creditHourSession": 1,
      "hoursWeek": 1,
      "room": "VARIED",
      "days": [],
      "dayNames": []
    }
  },
  {
    "termDesc": "Spring 2022",
    "CRN": "6045",
    "courseNumber": "118",
    "sequenceNumber": "03",
    "subjectDescription": "KNES Kinesiology &amp; Health Sci",
    "scheduleTypeDescription": "Basketball - Women",
    "courseTitle": "Varsity Basketball - Women",
    "creditHours": null,
    "maximumEnrollment": 50,
    "waitCapacity": 50,
    "creditHourHigh": null,
    "creditHourLow": 1,
    "faculty": [
      {
        "bannerId": "366118",
        "displayName": "Nakamura, Alan",
        "emailAddress": "alan.nakamura@biola.edu",
        "primaryIndicator": true
      }
    ],
    "location": {
      "startDate": "01/10/2022",
      "endDate": "05/07/2022",
      "beginTime": null,
      "endTime": null,
      "building": "NONE",
      "buildingDescription": "None",
      "creditHourSession": 1,
      "hoursWeek": 1,
      "room": "ONLINE",
      "days": [],
      "dayNames": []
    }
  },
  {
    "termDesc": "Spring 2022",
    "CRN": "6046",
    "courseNumber": "118",
    "sequenceNumber": "04",
    "subjectDescription": "KNES Kinesiology &amp; Health Sci",
    "scheduleTypeDescription": "Golf - Women",
    "courseTitle": "Varsity Golf - Women",
    "creditHours": null,
    "maximumEnrollment": 50,
    "waitCapacity": 50,
    "creditHourHigh": null,
    "creditHourLow": 1,
    "faculty": [
      {
        "bannerId": "366119",
        "displayName": "Carr, Jane",
        "emailAddress": "jane.carr@biola.edu",
        "primaryIndicator": true
      }
    ],
    "location": {
      "startDate": "01/10/2022",
      "endDate": "05/07/2022",
      "beginTime": null,
      "endTime": null,
      "building": "NONE",
      "buildingDescription": "None",
      "creditHourSession": 1,
      "hoursWeek": 1,
      "room": "VARIED",
      "days": [],
      "dayNames": []
    }
  },
  {
    "termDesc": "Spring 2022",
    "CRN": "6047",
    "courseNumber": "118",
    "sequenceNumber": "05",
    "subjectDescription": "KNES Kinesiology &amp; Health Sci",
    "scheduleTypeDescription": "Cross-Country - Men",
    "courseTitle": "Varsity Cross Country - Men",
    "creditHours": null,
    "maximumEnrollment": 50,
    "waitCapacity": 50,
    "creditHourHigh": null,
    "creditHourLow": 1,
    "faculty": [
      {
        "bannerId": "366117",
        "displayName": "Henning, Sean",
        "emailAddress": "sean.henning@biola.edu",
        "primaryIndicator": true
      }
    ],
    "location": {
      "startDate": "01/10/2022",
      "endDate": "05/07/2022",
      "beginTime": null,
      "endTime": null,
      "building": "NONE",
      "buildingDescription": "None",
      "creditHourSession": 1,
      "hoursWeek": 1,
      "room": "VARIED",
      "days": [],
      "dayNames": []
    }
  },
  {
    "termDesc": "Spring 2022",
    "CRN": "6048",
    "courseNumber": "118",
    "sequenceNumber": "06",
    "subjectDescription": "KNES Kinesiology &amp; Health Sci",
    "scheduleTypeDescription": "Cross-Country - Women",
    "courseTitle": "Varsity Cross Country - Women",
    "creditHours": null,
    "maximumEnrollment": 50,
    "waitCapacity": 50,
    "creditHourHigh": null,
    "creditHourLow": 1,
    "faculty": [
      {
        "bannerId": "366117",
        "displayName": "Henning, Sean",
        "emailAddress": "sean.henning@biola.edu",
        "primaryIndicator": true
      }
    ],
    "location": {
      "startDate": "01/10/2022",
      "endDate": "05/07/2022",
      "beginTime": null,
      "endTime": null,
      "building": "NONE",
      "buildingDescription": "None",
      "creditHourSession": 1,
      "hoursWeek": 1,
      "room": "VARIED",
      "days": [],
      "dayNames": []
    }
  },
  {
    "termDesc": "Spring 2022",
    "CRN": "6049",
    "courseNumber": "118",
    "sequenceNumber": "07",
    "subjectDescription": "KNES Kinesiology &amp; Health Sci",
    "scheduleTypeDescription": "Track &amp; Field - Men",
    "courseTitle": "Varsity Cross Country - Men",
    "creditHours": null,
    "maximumEnrollment": 50,
    "waitCapacity": 50,
    "creditHourHigh": null,
    "creditHourLow": 1,
    "faculty": [
      {
        "bannerId": "366117",
        "displayName": "Henning, Sean",
        "emailAddress": "sean.henning@biola.edu",
        "primaryIndicator": true
      }
    ],
    "location": {
      "startDate": "01/10/2022",
      "endDate": "05/07/2022",
      "beginTime": null,
      "endTime": null,
      "building": "NONE",
      "buildingDescription": "None",
      "creditHourSession": 1,
      "hoursWeek": 1,
      "room": "VARIED",
      "days": [],
      "dayNames": []
    }
  },
  {
    "termDesc": "Spring 2022",
    "CRN": "6050",
    "courseNumber": "118",
    "sequenceNumber": "08",
    "subjectDescription": "KNES Kinesiology &amp; Health Sci",
    "scheduleTypeDescription": "Track &amp; Field - Women",
    "courseTitle": "Varsity Track/Field - Women",
    "creditHours": null,
    "maximumEnrollment": 50,
    "waitCapacity": 50,
    "creditHourHigh": null,
    "creditHourLow": 1,
    "faculty": [
      {
        "bannerId": "366117",
        "displayName": "Henning, Sean",
        "emailAddress": "sean.henning@biola.edu",
        "primaryIndicator": true
      }
    ],
    "location": {
      "startDate": "01/10/2022",
      "endDate": "05/07/2022",
      "beginTime": null,
      "endTime": null,
      "building": "NONE",
      "buildingDescription": "None",
      "creditHourSession": 1,
      "hoursWeek": 1,
      "room": "VARIED",
      "days": [],
      "dayNames": []
    }
  },
  {
    "termDesc": "Spring 2022",
    "CRN": "6051",
    "courseNumber": "118",
    "sequenceNumber": "09",
    "subjectDescription": "KNES Kinesiology &amp; Health Sci",
    "scheduleTypeDescription": "Swimming - Men",
    "courseTitle": "Varsity Swim - Men",
    "creditHours": null,
    "maximumEnrollment": 50,
    "waitCapacity": 50,
    "creditHourHigh": null,
    "creditHourLow": 1,
    "faculty": [
      {
        "bannerId": "366120",
        "displayName": "Harding, Nathan",
        "emailAddress": "nathan.harding@biola.edu",
        "primaryIndicator": true
      }
    ],
    "location": {
      "startDate": "01/10/2022",
      "endDate": "05/07/2022",
      "beginTime": null,
      "endTime": null,
      "building": "NONE",
      "buildingDescription": "None",
      "creditHourSession": 1,
      "hoursWeek": 1,
      "room": "VARIED",
      "days": [],
      "dayNames": []
    }
  },
  {
    "termDesc": "Spring 2022",
    "CRN": "6052",
    "courseNumber": "118",
    "sequenceNumber": "10",
    "subjectDescription": "KNES Kinesiology &amp; Health Sci",
    "scheduleTypeDescription": "Swimming - Women",
    "courseTitle": "Varsity Swim - Women",
    "creditHours": null,
    "maximumEnrollment": 50,
    "waitCapacity": 50,
    "creditHourHigh": null,
    "creditHourLow": 1,
    "faculty": [
      {
        "bannerId": "366120",
        "displayName": "Harding, Nathan",
        "emailAddress": "nathan.harding@biola.edu",
        "primaryIndicator": true
      }
    ],
    "location": {
      "startDate": "01/10/2022",
      "endDate": "05/07/2022",
      "beginTime": null,
      "endTime": null,
      "building": "NONE",
      "buildingDescription": "None",
      "creditHourSession": 1,
      "hoursWeek": 1,
      "room": "VARIED",
      "days": [],
      "dayNames": []
    }
  },
  {
    "termDesc": "Spring 2022",
    "CRN": "6053",
    "courseNumber": "118",
    "sequenceNumber": "11",
    "subjectDescription": "KNES Kinesiology &amp; Health Sci",
    "scheduleTypeDescription": "Soccer - Men",
    "courseTitle": "Varsity Soccer - Men",
    "creditHours": null,
    "maximumEnrollment": 50,
    "waitCapacity": 50,
    "creditHourHigh": null,
    "creditHourLow": 1,
    "faculty": [
      {
        "bannerId": "366121",
        "displayName": "O&#39;Keefe, Joseph",
        "emailAddress": "joseph.d.okeefe@biola.edu",
        "primaryIndicator": true
      }
    ],
    "location": {
      "startDate": "01/10/2022",
      "endDate": "05/07/2022",
      "beginTime": null,
      "endTime": null,
      "building": "NONE",
      "buildingDescription": "None",
      "creditHourSession": 1,
      "hoursWeek": 1,
      "room": "VARIED",
      "days": [],
      "dayNames": []
    }
  },
  {
    "termDesc": "Spring 2022",
    "CRN": "6054",
    "courseNumber": "118",
    "sequenceNumber": "12",
    "subjectDescription": "KNES Kinesiology &amp; Health Sci",
    "scheduleTypeDescription": "Soccer - Women",
    "courseTitle": "Varsity Soccer - Women",
    "creditHours": null,
    "maximumEnrollment": 50,
    "waitCapacity": 50,
    "creditHourHigh": null,
    "creditHourLow": 1,
    "faculty": [
      {
        "bannerId": "366122",
        "displayName": "Brunelle, Erin",
        "emailAddress": "erin.brunelle@biola.edu",
        "primaryIndicator": true
      }
    ],
    "location": {
      "startDate": "01/10/2022",
      "endDate": "05/07/2022",
      "beginTime": null,
      "endTime": null,
      "building": "NONE",
      "buildingDescription": "None",
      "creditHourSession": 1,
      "hoursWeek": 1,
      "room": "VARIED",
      "days": [],
      "dayNames": []
    }
  },
  {
    "termDesc": "Spring 2022",
    "CRN": "6055",
    "courseNumber": "118",
    "sequenceNumber": "13",
    "subjectDescription": "KNES Kinesiology &amp; Health Sci",
    "scheduleTypeDescription": "Tennis - Men",
    "courseTitle": "Varsity Tennis - Men",
    "creditHours": null,
    "maximumEnrollment": 50,
    "waitCapacity": 50,
    "creditHourHigh": null,
    "creditHourLow": 1,
    "faculty": [
      {
        "bannerId": "366116",
        "displayName": "Goodman, David",
        "emailAddress": "david.t.goodman@biola.edu",
        "primaryIndicator": true
      }
    ],
    "location": {
      "startDate": "01/10/2022",
      "endDate": "05/07/2022",
      "beginTime": null,
      "endTime": null,
      "building": "NONE",
      "buildingDescription": "None",
      "creditHourSession": 1,
      "hoursWeek": 1,
      "room": "VARIED",
      "days": [],
      "dayNames": []
    }
  },
  {
    "termDesc": "Spring 2022",
    "CRN": "6056",
    "courseNumber": "118",
    "sequenceNumber": "14",
    "subjectDescription": "KNES Kinesiology &amp; Health Sci",
    "scheduleTypeDescription": "Tennis - Women",
    "courseTitle": "Varsity Tennis - Women",
    "creditHours": null,
    "maximumEnrollment": 50,
    "waitCapacity": 50,
    "creditHourHigh": null,
    "creditHourLow": 1,
    "faculty": [
      {
        "bannerId": "366116",
        "displayName": "Goodman, David",
        "emailAddress": "david.t.goodman@biola.edu",
        "primaryIndicator": true
      }
    ],
    "location": {
      "startDate": "01/10/2022",
      "endDate": "05/07/2022",
      "beginTime": null,
      "endTime": null,
      "building": "NONE",
      "buildingDescription": "None",
      "creditHourSession": 1,
      "hoursWeek": 1,
      "room": "VARIED",
      "days": [],
      "dayNames": []
    }
  },
  {
    "termDesc": "Spring 2022",
    "CRN": "6057",
    "courseNumber": "118",
    "sequenceNumber": "15",
    "subjectDescription": "KNES Kinesiology &amp; Health Sci",
    "scheduleTypeDescription": "Volleyball - Women",
    "courseTitle": "Varsity Volleyball - Women",
    "creditHours": null,
    "maximumEnrollment": 50,
    "waitCapacity": 50,
    "creditHourHigh": null,
    "creditHourLow": 1,
    "faculty": [
      {
        "bannerId": "366128",
        "displayName": "Seltzer, Aaron",
        "emailAddress": "aaron.seltzer@biola.edu",
        "primaryIndicator": true
      }
    ],
    "location": {
      "startDate": "01/10/2022",
      "endDate": "05/07/2022",
      "beginTime": null,
      "endTime": null,
      "building": "NONE",
      "buildingDescription": "None",
      "creditHourSession": 1,
      "hoursWeek": 1,
      "room": "VARIED",
      "days": [],
      "dayNames": []
    }
  },
  {
    "termDesc": "Spring 2022",
    "CRN": "6058",
    "courseNumber": "118",
    "sequenceNumber": "16",
    "subjectDescription": "KNES Kinesiology &amp; Health Sci",
    "scheduleTypeDescription": "Softball - Women",
    "courseTitle": "Varsity Softball - Women",
    "creditHours": null,
    "maximumEnrollment": 50,
    "waitCapacity": 50,
    "creditHourHigh": null,
    "creditHourLow": 1,
    "faculty": [],
    "location": {
      "startDate": "01/10/2022",
      "endDate": "05/07/2022",
      "beginTime": null,
      "endTime": null,
      "building": "NONE",
      "buildingDescription": "None",
      "creditHourSession": 1,
      "hoursWeek": 1,
      "room": "VARIED",
      "days": [],
      "dayNames": []
    }
  },
  {
    "termDesc": "Spring 2022",
    "CRN": "6059",
    "courseNumber": "118",
    "sequenceNumber": "17",
    "subjectDescription": "KNES Kinesiology &amp; Health Sci",
    "scheduleTypeDescription": "Water Polo - Men",
    "courseTitle": "Varsity Men&#39;s Water Polo",
    "creditHours": null,
    "maximumEnrollment": 50,
    "waitCapacity": 50,
    "creditHourHigh": null,
    "creditHourLow": 1,
    "faculty": [
      {
        "bannerId": "366129",
        "displayName": "Nordell, Rick",
        "emailAddress": "rick.nordell@biola.edu",
        "primaryIndicator": true
      }
    ],
    "location": {
      "startDate": "01/10/2022",
      "endDate": "05/07/2022",
      "beginTime": null,
      "endTime": null,
      "building": "NONE",
      "buildingDescription": "None",
      "creditHourSession": 1,
      "hoursWeek": 1,
      "room": "VARIED",
      "days": [],
      "dayNames": []
    }
  },
  {
    "termDesc": "Spring 2022",
    "CRN": "6060",
    "courseNumber": "118",
    "sequenceNumber": "18",
    "subjectDescription": "KNES Kinesiology &amp; Health Sci",
    "scheduleTypeDescription": "Water Polo - Women",
    "courseTitle": "Varsity Women&#39;s Water Polo",
    "creditHours": null,
    "maximumEnrollment": 50,
    "waitCapacity": 50,
    "creditHourHigh": null,
    "creditHourLow": 1,
    "faculty": [
      {
        "bannerId": "366130",
        "displayName": "Orozco, Sarah",
        "emailAddress": "sarah.orozco@biola.edu",
        "primaryIndicator": true
      }
    ],
    "location": {
      "startDate": "01/10/2022",
      "endDate": "05/07/2022",
      "beginTime": null,
      "endTime": null,
      "building": "NONE",
      "buildingDescription": "None",
      "creditHourSession": 1,
      "hoursWeek": 1,
      "room": "VARIED",
      "days": [],
      "dayNames": []
    }
  },
  {
    "termDesc": "Spring 2022",
    "CRN": "6003",
    "courseNumber": "130",
    "sequenceNumber": "02",
    "subjectDescription": "KNES Kinesiology &amp; Health Sci",
    "scheduleTypeDescription": "Swimming",
    "courseTitle": "Int Swimming",
    "creditHours": null,
    "maximumEnrollment": 20,
    "waitCapacity": 30,
    "creditHourHigh": null,
    "creditHourLow": 1,
    "faculty": [
      {
        "bannerId": "366104",
        "displayName": "Cook, Nathanael",
        "emailAddress": "nathanael.d.cook@biola.edu",
        "primaryIndicator": true
      }
    ],
    "location": {
      "startDate": "01/10/2022",
      "endDate": "04/30/2022",
      "beginTime": "1100",
      "endTime": "1150",
      "building": "LANSNG",
      "buildingDescription": "Lansing Aquatic Center",
      "creditHourSession": 1,
      "hoursWeek": 1.66,
      "room": "POOL",
      "days": [
        "M",
        "W"
      ],
      "dayNames": [
        "Monday",
        "Wednesday"
      ]
    }
  },
  {
    "termDesc": "Spring 2022",
    "CRN": "6039",
    "courseNumber": "130",
    "sequenceNumber": "33",
    "subjectDescription": "KNES Kinesiology &amp; Health Sci",
    "scheduleTypeDescription": "Tennis",
    "courseTitle": "Int Tennis",
    "creditHours": null,
    "maximumEnrollment": 14,
    "waitCapacity": 14,
    "creditHourHigh": null,
    "creditHourLow": 1,
    "faculty": [
      {
        "bannerId": "366116",
        "displayName": "Goodman, David",
        "emailAddress": "david.t.goodman@biola.edu",
        "primaryIndicator": true
      }
    ],
    "location": {
      "startDate": "01/10/2022",
      "endDate": "04/30/2022",
      "beginTime": "1030",
      "endTime": "1200",
      "building": "TENNIS",
      "buildingDescription": "Tennis Center",
      "creditHourSession": 1,
      "hoursWeek": 3,
      "room": "COURTS",
      "days": [
        "T",
        "R"
      ],
      "dayNames": [
        "Tuesday",
        "Thursday"
      ]
    }
  },
  {
    "termDesc": "Spring 2022",
    "CRN": "6013",
    "courseNumber": "150",
    "sequenceNumber": "12",
    "subjectDescription": "KNES Kinesiology &amp; Health Sci",
    "scheduleTypeDescription": "Archery",
    "courseTitle": "Adv Archery",
    "creditHours": null,
    "maximumEnrollment": 20,
    "waitCapacity": 25,
    "creditHourHigh": null,
    "creditHourLow": 1,
    "faculty": [
      {
        "bannerId": "366106",
        "displayName": "Gardner, Jacob",
        "emailAddress": "jake.gardner@biola.edu",
        "primaryIndicator": true
      }
    ],
    "location": {
      "startDate": "01/14/2022",
      "endDate": "01/14/2022",
      "beginTime": "1030",
      "endTime": "1200",
      "building": "SUTHLD",
      "buildingDescription": "Sutherland Hall",
      "creditHourSession": 1,
      "hoursWeek": 1.5,
      "room": "117",
      "days": [
        "F"
      ],
      "dayNames": [
        "Friday"
      ]
    }
  },
  {
    "termDesc": "Spring 2022",
    "CRN": "6018",
    "courseNumber": "150",
    "sequenceNumber": "15",
    "subjectDescription": "KNES Kinesiology &amp; Health Sci",
    "scheduleTypeDescription": "Volleyball",
    "courseTitle": "Adv Volleyball",
    "creditHours": null,
    "maximumEnrollment": 24,
    "waitCapacity": 26,
    "creditHourHigh": null,
    "creditHourLow": 1,
    "faculty": [
      {
        "bannerId": "366108",
        "displayName": "Teague, Grace",
        "emailAddress": "grace.l.gallarda@biola.edu",
        "primaryIndicator": true
      }
    ],
    "location": {
      "startDate": "01/10/2022",
      "endDate": "04/30/2022",
      "beginTime": "1030",
      "endTime": "1120",
      "building": "CHASE",
      "buildingDescription": "Chase Gymnasium",
      "creditHourSession": 1,
      "hoursWeek": 1.66,
      "room": "GYMNASIUM",
      "days": [
        "T",
        "R"
      ],
      "dayNames": [
        "Tuesday",
        "Thursday"
      ]
    }
  },
  {
    "termDesc": "Spring 2022",
    "CRN": "6020",
    "courseNumber": "150",
    "sequenceNumber": "16",
    "subjectDescription": "KNES Kinesiology &amp; Health Sci",
    "scheduleTypeDescription": "Soccer",
    "courseTitle": "Adv Soccer - Coed",
    "creditHours": null,
    "maximumEnrollment": 22,
    "waitCapacity": 25,
    "creditHourHigh": null,
    "creditHourLow": 1,
    "faculty": [
      {
        "bannerId": "366109",
        "displayName": "Gizzi, Paul",
        "emailAddress": "paul.gizzi@biola.edu",
        "primaryIndicator": true
      }
    ],
    "location": {
      "startDate": "01/10/2022",
      "endDate": "04/30/2022",
      "beginTime": "1030",
      "endTime": "1120",
      "building": "ATHLTC",
      "buildingDescription": "Athletics",
      "creditHourSession": 1,
      "hoursWeek": 1.66,
      "room": "SOCCER",
      "days": [
        "M",
        "W"
      ],
      "dayNames": [
        "Monday",
        "Wednesday"
      ]
    }
  },
  {
    "termDesc": "Spring 2022",
    "CRN": "6032",
    "courseNumber": "150",
    "sequenceNumber": "30",
    "subjectDescription": "KNES Kinesiology &amp; Health Sci",
    "scheduleTypeDescription": "Basketball",
    "courseTitle": "Adv Basketball",
    "creditHours": null,
    "maximumEnrollment": 24,
    "waitCapacity": 24,
    "creditHourHigh": null,
    "creditHourLow": 1,
    "faculty": [
      {
        "bannerId": "366114",
        "displayName": "Cone, David",
        "emailAddress": "david.e.cone@biola.edu",
        "primaryIndicator": true
      }
    ],
    "location": {
      "startDate": "01/10/2022",
      "endDate": "04/30/2022",
      "beginTime": "1030",
      "endTime": "1129",
      "building": "CHASE",
      "buildingDescription": "Chase Gymnasium",
      "creditHourSession": 1,
      "hoursWeek": 1.96,
      "room": "GYMNASIUM",
      "days": [
        "M",
        "W"
      ],
      "dayNames": [
        "Monday",
        "Wednesday"
      ]
    }
  },
  {
    "termDesc": "Spring 2022",
    "CRN": "6034",
    "courseNumber": "150",
    "sequenceNumber": "31",
    "subjectDescription": "KNES Kinesiology &amp; Health Sci",
    "scheduleTypeDescription": "Basketball",
    "courseTitle": "Adv Basketball",
    "creditHours": null,
    "maximumEnrollment": 30,
    "waitCapacity": 25,
    "creditHourHigh": null,
    "creditHourLow": 1,
    "faculty": [
      {
        "bannerId": "366115",
        "displayName": "Holmquist, David",
        "emailAddress": "dave.holmquist@biola.edu",
        "primaryIndicator": true
      }
    ],
    "location": {
      "startDate": "01/10/2022",
      "endDate": "04/30/2022",
      "beginTime": "1200",
      "endTime": "1250",
      "building": "CHASE",
      "buildingDescription": "Chase Gymnasium",
      "creditHourSession": 1,
      "hoursWeek": 1.66,
      "room": "GYMNASIUM",
      "days": [
        "M",
        "W"
      ],
      "dayNames": [
        "Monday",
        "Wednesday"
      ]
    }
  },
  {
    "termDesc": "Spring 2022",
    "CRN": "6037",
    "courseNumber": "150",
    "sequenceNumber": "32",
    "subjectDescription": "KNES Kinesiology &amp; Health Sci",
    "scheduleTypeDescription": "Basketball",
    "courseTitle": "Adv Basketball",
    "creditHours": null,
    "maximumEnrollment": 30,
    "waitCapacity": 25,
    "creditHourHigh": null,
    "creditHourLow": 1,
    "faculty": [
      {
        "bannerId": "366115",
        "displayName": "Holmquist, David",
        "emailAddress": "dave.holmquist@biola.edu",
        "primaryIndicator": true
      }
    ],
    "location": {
      "startDate": "01/10/2022",
      "endDate": "04/30/2022",
      "beginTime": "1200",
      "endTime": "1250",
      "building": "CHASE",
      "buildingDescription": "Chase Gymnasium",
      "creditHourSession": 1,
      "hoursWeek": 1.66,
      "room": "GYMNASIUM",
      "days": [
        "T",
        "R"
      ],
      "dayNames": [
        "Tuesday",
        "Thursday"
      ]
    }
  },
  {
    "termDesc": "Spring 2022",
    "CRN": "6061",
    "courseNumber": "200",
    "sequenceNumber": "01",
    "subjectDescription": "KNES Kinesiology &amp; Health Sci",
    "scheduleTypeDescription": "Lecture/Standard",
    "courseTitle": "Public Health Principles and Practice",
    "creditHours": null,
    "maximumEnrollment": 24,
    "waitCapacity": 24,
    "creditHourHigh": null,
    "creditHourLow": 3,
    "faculty": [
      {
        "bannerId": "366124",
        "displayName": "Park, Ji-Yeun",
        "emailAddress": "ji.yeun.park@biola.edu",
        "primaryIndicator": true
      }
    ],
    "location": {
      "startDate": "01/10/2022",
      "endDate": "04/30/2022",
      "beginTime": "1330",
      "endTime": "1445",
      "building": "SOUBRU",
      "buildingDescription": "Soubirou Hall",
      "creditHourSession": 3,
      "hoursWeek": 2.5,
      "room": "102",
      "days": [
        "M",
        "W"
      ],
      "dayNames": [
        "Monday",
        "Wednesday"
      ]
    }
  },
  {
    "termDesc": "Spring 2022",
    "CRN": "6062",
    "courseNumber": "201",
    "sequenceNumber": "01",
    "subjectDescription": "KNES Kinesiology &amp; Health Sci",
    "scheduleTypeDescription": "Lecture/Standard",
    "courseTitle": "Elementary Physical Education Methods and Activities",
    "creditHours": null,
    "maximumEnrollment": 28,
    "waitCapacity": 28,
    "creditHourHigh": null,
    "creditHourLow": 2,
    "faculty": [
      {
        "bannerId": "366052",
        "displayName": "Hahn, Jennifer",
        "emailAddress": "jennifer.hahn@biola.edu",
        "primaryIndicator": true
      }
    ],
    "location": {
      "startDate": "01/10/2022",
      "endDate": "04/30/2022",
      "beginTime": "1030",
      "endTime": "1320",
      "building": "LIM",
      "buildingDescription": "Lim Center",
      "creditHourSession": 2,
      "hoursWeek": 2.83,
      "room": "043",
      "days": [
        "F"
      ],
      "dayNames": [
        "Friday"
      ]
    }
  },
  {
    "termDesc": "Spring 2022",
    "CRN": "6069",
    "courseNumber": "213",
    "sequenceNumber": "01",
    "subjectDescription": "KNES Kinesiology &amp; Health Sci",
    "scheduleTypeDescription": "Lecture/Standard",
    "courseTitle": "Scientific Principles of Health and Fitness",
    "creditHours": null,
    "maximumEnrollment": 20,
    "waitCapacity": 20,
    "creditHourHigh": null,
    "creditHourLow": 3,
    "faculty": [
      {
        "bannerId": "366127",
        "displayName": "Altamirano, Kristianna",
        "emailAddress": "kristianna.altamirano@biola.edu",
        "primaryIndicator": true
      }
    ],
    "location": {
      "startDate": "01/10/2022",
      "endDate": "04/30/2022",
      "beginTime": "1800",
      "endTime": "2050",
      "building": "SOUBRU",
      "buildingDescription": "Soubirou Hall",
      "creditHourSession": 3,
      "hoursWeek": 2.83,
      "room": "102",
      "days": [
        "R"
      ],
      "dayNames": [
        "Thursday"
      ]
    }
  },
  {
    "termDesc": "Spring 2022",
    "CRN": "6732",
    "courseNumber": "301",
    "sequenceNumber": "01",
    "subjectDescription": "KNES Kinesiology &amp; Health Sci",
    "scheduleTypeDescription": "Lecture/Standard",
    "courseTitle": "Kinesiology",
    "creditHours": null,
    "maximumEnrollment": 26,
    "waitCapacity": 26,
    "creditHourHigh": null,
    "creditHourLow": 3,
    "faculty": [
      {
        "bannerId": "366106",
        "displayName": "Gardner, Jacob",
        "emailAddress": "jake.gardner@biola.edu",
        "primaryIndicator": true
      }
    ],
    "location": {
      "startDate": "01/10/2022",
      "endDate": "05/07/2022",
      "beginTime": null,
      "endTime": null,
      "building": "NONE",
      "buildingDescription": "None",
      "creditHourSession": 3,
      "hoursWeek": 3,
      "room": "ONLINE",
      "days": [],
      "dayNames": []
    }
  },
  {
    "termDesc": "Spring 2022",
    "CRN": "6070",
    "courseNumber": "302",
    "sequenceNumber": "01",
    "subjectDescription": "KNES Kinesiology &amp; Health Sci",
    "scheduleTypeDescription": "Lecture/Standard",
    "courseTitle": "Exercise Physiology",
    "creditHours": null,
    "maximumEnrollment": 24,
    "waitCapacity": 24,
    "creditHourHigh": null,
    "creditHourLow": 3,
    "faculty": [
      {
        "bannerId": "366110",
        "displayName": "Apkarian, Marc",
        "emailAddress": "marc.apkarian@biola.edu",
        "primaryIndicator": true
      }
    ],
    "location": {
      "startDate": "01/10/2022",
      "endDate": "04/30/2022",
      "beginTime": "1030",
      "endTime": "1145",
      "building": "SOUBRU",
      "buildingDescription": "Soubirou Hall",
      "creditHourSession": 3,
      "hoursWeek": 2.5,
      "room": "102",
      "days": [
        "T",
        "R"
      ],
      "dayNames": [
        "Tuesday",
        "Thursday"
      ]
    }
  },
  {
    "termDesc": "Spring 2022",
    "CRN": "6071",
    "courseNumber": "303",
    "sequenceNumber": "01",
    "subjectDescription": "KNES Kinesiology &amp; Health Sci",
    "scheduleTypeDescription": "Lab",
    "courseTitle": "Exercise Physiology Laboratory",
    "creditHours": null,
    "maximumEnrollment": 12,
    "waitCapacity": 12,
    "creditHourHigh": null,
    "creditHourLow": 1,
    "faculty": [
      {
        "bannerId": "366110",
        "displayName": "Apkarian, Marc",
        "emailAddress": "marc.apkarian@biola.edu",
        "primaryIndicator": true
      }
    ],
    "location": {
      "startDate": "01/10/2022",
      "endDate": "04/30/2022",
      "beginTime": "1500",
      "endTime": "1750",
      "building": "LIM",
      "buildingDescription": "Lim Center",
      "creditHourSession": 1,
      "hoursWeek": 2.83,
      "room": "177",
      "days": [
        "T"
      ],
      "dayNames": [
        "Tuesday"
      ]
    }
  },
  {
    "termDesc": "Spring 2022",
    "CRN": "6072",
    "courseNumber": "303",
    "sequenceNumber": "02",
    "subjectDescription": "KNES Kinesiology &amp; Health Sci",
    "scheduleTypeDescription": "Lab",
    "courseTitle": "Exercise Physiology Laboratory",
    "creditHours": null,
    "maximumEnrollment": 12,
    "waitCapacity": 12,
    "creditHourHigh": null,
    "creditHourLow": 1,
    "faculty": [
      {
        "bannerId": "366110",
        "displayName": "Apkarian, Marc",
        "emailAddress": "marc.apkarian@biola.edu",
        "primaryIndicator": true
      }
    ],
    "location": {
      "startDate": "01/10/2022",
      "endDate": "04/30/2022",
      "beginTime": "1500",
      "endTime": "1750",
      "building": "LIM",
      "buildingDescription": "Lim Center",
      "creditHourSession": 1,
      "hoursWeek": 2.83,
      "room": "177",
      "days": [
        "R"
      ],
      "dayNames": [
        "Thursday"
      ]
    }
  },
  {
    "termDesc": "Spring 2022",
    "CRN": "6733",
    "courseNumber": "307",
    "sequenceNumber": "01",
    "subjectDescription": "KNES Kinesiology &amp; Health Sci",
    "scheduleTypeDescription": "Lecture/Standard",
    "courseTitle": "Measurement and Evaluation in Kinesiology",
    "creditHours": null,
    "maximumEnrollment": 18,
    "waitCapacity": 18,
    "creditHourHigh": null,
    "creditHourLow": 3,
    "faculty": [
      {
        "bannerId": "366127",
        "displayName": "Altamirano, Kristianna",
        "emailAddress": "kristianna.altamirano@biola.edu",
        "primaryIndicator": true
      }
    ],
    "location": {
      "startDate": "01/10/2022",
      "endDate": "04/30/2022",
      "beginTime": "1200",
      "endTime": "1315",
      "building": "SOUBRU",
      "buildingDescription": "Soubirou Hall",
      "creditHourSession": 0,
      "hoursWeek": 2.5,
      "room": "102",
      "days": [
        "T",
        "R"
      ],
      "dayNames": [
        "Tuesday",
        "Thursday"
      ]
    }
  },
  {
    "termDesc": "Spring 2022",
    "CRN": "6726",
    "courseNumber": "320",
    "sequenceNumber": "01",
    "subjectDescription": "KNES Kinesiology &amp; Health Sci",
    "scheduleTypeDescription": "Lecture/Standard",
    "courseTitle": "Health Behavior and Health Promotion",
    "creditHours": null,
    "maximumEnrollment": 25,
    "waitCapacity": 25,
    "creditHourHigh": null,
    "creditHourLow": 3,
    "faculty": [
      {
        "bannerId": "366131",
        "displayName": "Walker, Danielle",
        "emailAddress": "danielle.walker@biola.edu",
        "primaryIndicator": true
      }
    ],
    "location": {
      "startDate": "01/10/2022",
      "endDate": "02/26/2022",
      "beginTime": "1200",
      "endTime": "1300",
      "building": "SUTHLD",
      "buildingDescription": "Sutherland Hall",
      "creditHourSession": 0,
      "hoursWeek": 1,
      "room": "118",
      "days": [
        "M"
      ],
      "dayNames": [
        "Monday"
      ]
    }
  },
  {
    "termDesc": "Spring 2022",
    "CRN": "6728",
    "courseNumber": "325",
    "sequenceNumber": "01",
    "subjectDescription": "KNES Kinesiology &amp; Health Sci",
    "scheduleTypeDescription": "Lecture/Standard",
    "courseTitle": "Environmental Health",
    "creditHours": null,
    "maximumEnrollment": 18,
    "waitCapacity": 18,
    "creditHourHigh": null,
    "creditHourLow": 3,
    "faculty": [
      {
        "bannerId": "366132",
        "displayName": "Peterson, Brent",
        "emailAddress": "brent.peterson@biola.edu",
        "primaryIndicator": true
      },
      {
        "bannerId": "365951",
        "displayName": "Sun, Patrick",
        "emailAddress": "patrick.sun@biola.edu",
        "primaryIndicator": false
      }
    ],
    "location": {
      "startDate": "03/07/2022",
      "endDate": "04/23/2022",
      "beginTime": "1500",
      "endTime": "1600",
      "building": "MYERS",
      "buildingDescription": "Myers Hall",
      "creditHourSession": 0,
      "hoursWeek": 1,
      "room": "110",
      "days": [
        "T"
      ],
      "dayNames": [
        "Tuesday"
      ]
    }
  },
  {
    "termDesc": "Spring 2022",
    "CRN": "6730",
    "courseNumber": "330",
    "sequenceNumber": "01",
    "subjectDescription": "KNES Kinesiology &amp; Health Sci",
    "scheduleTypeDescription": "Lecture/Standard",
    "courseTitle": "Global Health Leadership",
    "creditHours": null,
    "maximumEnrollment": 18,
    "waitCapacity": 18,
    "creditHourHigh": null,
    "creditHourLow": 3,
    "faculty": [
      {
        "bannerId": "366131",
        "displayName": "Walker, Danielle",
        "emailAddress": "danielle.walker@biola.edu",
        "primaryIndicator": true
      }
    ],
    "location": {
      "startDate": "03/07/2022",
      "endDate": "04/23/2022",
      "beginTime": "1200",
      "endTime": "1300",
      "building": "LIM",
      "buildingDescription": "Lim Center",
      "creditHourSession": 0,
      "hoursWeek": 1,
      "room": "042",
      "days": [
        "W"
      ],
      "dayNames": [
        "Wednesday"
      ]
    }
  },
  {
    "termDesc": "Spring 2022",
    "CRN": "6074",
    "courseNumber": "402",
    "sequenceNumber": "01",
    "subjectDescription": "KNES Kinesiology &amp; Health Sci",
    "scheduleTypeDescription": "Lecture/Standard",
    "courseTitle": "Evidence Based Sports Medicine",
    "creditHours": null,
    "maximumEnrollment": 18,
    "waitCapacity": 18,
    "creditHourHigh": null,
    "creditHourLow": 3,
    "faculty": [
      {
        "bannerId": "366106",
        "displayName": "Gardner, Jacob",
        "emailAddress": "jake.gardner@biola.edu",
        "primaryIndicator": true
      }
    ],
    "location": {
      "startDate": "01/10/2022",
      "endDate": "04/30/2022",
      "beginTime": "0800",
      "endTime": "0915",
      "building": "SOUBRU",
      "buildingDescription": "Soubirou Hall",
      "creditHourSession": 3,
      "hoursWeek": 2.5,
      "room": "102",
      "days": [
        "M",
        "W"
      ],
      "dayNames": [
        "Monday",
        "Wednesday"
      ]
    }
  },
  {
    "termDesc": "Spring 2022",
    "CRN": "6078",
    "courseNumber": "408",
    "sequenceNumber": "01",
    "subjectDescription": "KNES Kinesiology &amp; Health Sci",
    "scheduleTypeDescription": "Lecture/Standard",
    "courseTitle": "Motor Learning",
    "creditHours": null,
    "maximumEnrollment": 26,
    "waitCapacity": 26,
    "creditHourHigh": null,
    "creditHourLow": 3,
    "faculty": [
      {
        "bannerId": "366132",
        "displayName": "Peterson, Brent",
        "emailAddress": "brent.peterson@biola.edu",
        "primaryIndicator": true
      }
    ],
    "location": {
      "startDate": "01/10/2022",
      "endDate": "04/30/2022",
      "beginTime": "0730",
      "endTime": "0845",
      "building": "SOUBRU",
      "buildingDescription": "Soubirou Hall",
      "creditHourSession": 3,
      "hoursWeek": 2.5,
      "room": "102",
      "days": [
        "T",
        "R"
      ],
      "dayNames": [
        "Tuesday",
        "Thursday"
      ]
    }
  },
  {
    "termDesc": "Spring 2022",
    "CRN": "6079",
    "courseNumber": "422",
    "sequenceNumber": "01",
    "subjectDescription": "KNES Kinesiology &amp; Health Sci",
    "scheduleTypeDescription": "Lecture/Standard",
    "courseTitle": "Biomechanics",
    "creditHours": null,
    "maximumEnrollment": 18,
    "waitCapacity": 18,
    "creditHourHigh": null,
    "creditHourLow": 3,
    "faculty": [
      {
        "bannerId": "366106",
        "displayName": "Gardner, Jacob",
        "emailAddress": "jake.gardner@biola.edu",
        "primaryIndicator": true
      }
    ],
    "location": {
      "startDate": "01/10/2022",
      "endDate": "04/30/2022",
      "beginTime": "1030",
      "endTime": "1145",
      "building": "SOUBRU",
      "buildingDescription": "Soubirou Hall",
      "creditHourSession": 3,
      "hoursWeek": 2.5,
      "room": "102",
      "days": [
        "M",
        "W"
      ],
      "dayNames": [
        "Monday",
        "Wednesday"
      ]
    }
  },
  {
    "termDesc": "Spring 2022",
    "CRN": "6080",
    "courseNumber": "423",
    "sequenceNumber": "01",
    "subjectDescription": "KNES Kinesiology &amp; Health Sci",
    "scheduleTypeDescription": "Lab",
    "courseTitle": "Biomechanics Laboratory",
    "creditHours": null,
    "maximumEnrollment": 18,
    "waitCapacity": 18,
    "creditHourHigh": null,
    "creditHourLow": 1,
    "faculty": [
      {
        "bannerId": "366106",
        "displayName": "Gardner, Jacob",
        "emailAddress": "jake.gardner@biola.edu",
        "primaryIndicator": true
      }
    ],
    "location": {
      "startDate": "01/10/2022",
      "endDate": "04/30/2022",
      "beginTime": "1330",
      "endTime": "1620",
      "building": "SOUBRU",
      "buildingDescription": "Soubirou Hall",
      "creditHourSession": 1,
      "hoursWeek": 2.83,
      "room": "101",
      "days": [
        "F"
      ],
      "dayNames": [
        "Friday"
      ]
    }
  },
  {
    "termDesc": "Spring 2022",
    "CRN": "6081",
    "courseNumber": "434",
    "sequenceNumber": "01",
    "subjectDescription": "KNES Kinesiology &amp; Health Sci",
    "scheduleTypeDescription": "Lecture/Standard",
    "courseTitle": "Leadership in Sport and Human Movement",
    "creditHours": null,
    "maximumEnrollment": 26,
    "waitCapacity": 26,
    "creditHourHigh": null,
    "creditHourLow": 3,
    "faculty": [
      {
        "bannerId": "366125",
        "displayName": "Miller, Kelsey",
        "emailAddress": "kelsey.l.miller@biola.edu",
        "primaryIndicator": true
      }
    ],
    "location": {
      "startDate": "01/10/2022",
      "endDate": "04/30/2022",
      "beginTime": "1330",
      "endTime": "1445",
      "building": "SOUBRU",
      "buildingDescription": "Soubirou Hall",
      "creditHourSession": 3,
      "hoursWeek": 2.5,
      "room": "102",
      "days": [
        "T",
        "R"
      ],
      "dayNames": [
        "Tuesday",
        "Thursday"
      ]
    }
  },
  {
    "termDesc": "Spring 2022",
    "CRN": "6082",
    "courseNumber": "440",
    "sequenceNumber": "01",
    "subjectDescription": "KNES Kinesiology &amp; Health Sci",
    "scheduleTypeDescription": "Lecture/Standard",
    "courseTitle": "Nutrition and Human Metabolism",
    "creditHours": null,
    "maximumEnrollment": 24,
    "waitCapacity": 24,
    "creditHourHigh": null,
    "creditHourLow": 3,
    "faculty": [
      {
        "bannerId": "366132",
        "displayName": "Peterson, Brent",
        "emailAddress": "brent.peterson@biola.edu",
        "primaryIndicator": true
      }
    ],
    "location": {
      "startDate": "01/10/2022",
      "endDate": "04/30/2022",
      "beginTime": "1500",
      "endTime": "1750",
      "building": "SOUBRU",
      "buildingDescription": "Soubirou Hall",
      "creditHourSession": 3,
      "hoursWeek": 2.83,
      "room": "102",
      "days": [
        "M"
      ],
      "dayNames": [
        "Monday"
      ]
    }
  },
  {
    "termDesc": "Spring 2022",
    "CRN": "6083",
    "courseNumber": "446",
    "sequenceNumber": "01",
    "subjectDescription": "KNES Kinesiology &amp; Health Sci",
    "scheduleTypeDescription": "Lecture/Standard",
    "courseTitle": "Functional Assessment and the Prescription of Exercise",
    "creditHours": null,
    "maximumEnrollment": 24,
    "waitCapacity": 12,
    "creditHourHigh": null,
    "creditHourLow": 3,
    "faculty": [
      {
        "bannerId": "366132",
        "displayName": "Peterson, Brent",
        "emailAddress": "brent.peterson@biola.edu",
        "primaryIndicator": true
      }
    ],
    "location": {
      "startDate": "01/10/2022",
      "endDate": "04/30/2022",
      "beginTime": "0900",
      "endTime": "1015",
      "building": "SOUBRU",
      "buildingDescription": "Soubirou Hall",
      "creditHourSession": 3,
      "hoursWeek": 2.5,
      "room": "102",
      "days": [
        "T",
        "R"
      ],
      "dayNames": [
        "Tuesday",
        "Thursday"
      ]
    }
  },
  {
    "termDesc": "Spring 2022",
    "CRN": "6084",
    "courseNumber": "447",
    "sequenceNumber": "01",
    "subjectDescription": "KNES Kinesiology &amp; Health Sci",
    "scheduleTypeDescription": "Lab",
    "courseTitle": "Functional Assessment and Prescription of Exercise Laboratory",
    "creditHours": null,
    "maximumEnrollment": 12,
    "waitCapacity": 12,
    "creditHourHigh": null,
    "creditHourLow": 1,
    "faculty": [
      {
        "bannerId": "366132",
        "displayName": "Peterson, Brent",
        "emailAddress": "brent.peterson@biola.edu",
        "primaryIndicator": true
      }
    ],
    "location": {
      "startDate": "01/10/2022",
      "endDate": "04/30/2022",
      "beginTime": "1030",
      "endTime": "1320",
      "building": "LIM",
      "buildingDescription": "Lim Center",
      "creditHourSession": 1,
      "hoursWeek": 2.83,
      "room": "177",
      "days": [
        "F"
      ],
      "dayNames": [
        "Friday"
      ]
    }
  },
  {
    "termDesc": "Spring 2022",
    "CRN": "6085",
    "courseNumber": "460",
    "sequenceNumber": "01",
    "subjectDescription": "KNES Kinesiology &amp; Health Sci",
    "scheduleTypeDescription": "Topic",
    "courseTitle": "TP: Exercise Prof Cert Prep",
    "creditHours": 3,
    "maximumEnrollment": 18,
    "waitCapacity": 18,
    "creditHourHigh": 3,
    "creditHourLow": 1,
    "faculty": [
      {
        "bannerId": "366110",
        "displayName": "Apkarian, Marc",
        "emailAddress": "marc.apkarian@biola.edu",
        "primaryIndicator": true
      }
    ],
    "location": {
      "startDate": "01/10/2022",
      "endDate": "04/30/2022",
      "beginTime": "1200",
      "endTime": "1315",
      "building": "SOUBRU",
      "buildingDescription": "Soubirou Hall",
      "creditHourSession": 3,
      "hoursWeek": 2.5,
      "room": "102",
      "days": [
        "M",
        "W"
      ],
      "dayNames": [
        "Monday",
        "Wednesday"
      ]
    }
  }
]